{"_id":"626ff2913937t941721f3378b","device_id":"212121214444","code":"624ad22bed37c156e9e08feb","description":"Wellness","Device_id":"01aabbccdd030101","createdAt":"2022-05-02T09:32:41.535Z","updatedAt":"2022-05-02T09:32:41.535Z","occupancyStatus":0,"occupancyCount":0,"iaq":32,"staticIaqValue":36,"co2Value":400,"voc":0.3,"gasValue":85992,"temperature":29.8,"pressure":100415,"humidity":38.7,"lux":289.7,"batVolt":3340,"timestamp":"2022-05-03T13:13:51.661Z","gateway":{"_id":"626ff2913937941721f33788","gateway_id":"dca632d93183","region":"eu","city":"Harburg","state":"Hamburg","company":"AMT","company_unit":"AMT","washroom":{"sensors":["626fe58b3937941721f334cb","626ff2913937941721f3378b"],"_id":"626fe58b3937941721f334bf","type":"male","createdAt":"2022-05-02T14:07:07.846Z","updatedAt":"2022-05-02T15:02:41.536Z","__v":0},"createdAt":"2022-05-02T15:02:41.532Z","updatedAt":"2022-05-02T15:02:41.532Z","__v":0,"floor":{"washrooms":["626fe58b3937941721f334bf"],"rooms":[],"_id":"626fe58b3937941721f334c1","sign":"B1","description":"test ","index":-1,"createdAt":"2022-05-02T14:07:07.849Z","updatedAt":"2022-05-02T15:02:41.528Z","__v":0},"infrastructure":{"floors":["626fe58b3937941721f334c1"],"_id":"626fe58b3937941721f334c3","name":"abc","location":"uk","type":"building","createdAt":"2022-05-02T14:07:07.851Z","updatedAt":"2022-05-02T15:02:41.529Z","__v":0}},"washroom":{"sensors":["626fe58b3937941721f334cb","626ff2913937941721f3378b"],"_id":"626fe58b3937941721f334bf","type":"male","createdAt":"2022-05-02T14:07:07.846Z","updatedAt":"2022-05-02T15:02:41.536Z","__v":0},"floor":{"washrooms":["626fe58b3937941721f334bf"],"rooms":[],"_id":"626fe58b3937941721f334c1","sign":"B1","description":"test ","index":-1,"createdAt":"2022-05-02T14:07:07.849Z","updatedAt":"2022-05-02T15:02:41.528Z","__v":0},"infrastructure":{"floors":["626fe58b3937941721f334c1"],"_id":"626fe58b3937941721f334c3","name":"abc","location":"uk","type":"building","createdAt":"2022-05-02T14:07:07.851Z","updatedAt":"2022-05-02T15:02:41.529Z","__v":0},"sensor_configuration":[{"label":"temprature","defaultValue":1,"unit":"Celsius (°C)","startRange":1,"endRange":10,"description":"value should be lies in range(1-10)","selectedValue":1}]}